sparqlite/__init__.py
sparqlite/client.py
sparqlite/exceptions.py
sparqlite-1.1.0.dist-info/METADATA
sparqlite-1.1.0.dist-info/WHEEL
sparqlite-1.1.0.dist-info/licenses/LICENSE.md
sparqlite-1.1.0.dist-info/RECORD
