Metadata-Version: 2.4
Name: sparqlite
Version: 1.1.0
Summary: A modern, lightweight SPARQL 1.1 client for Python
License-File: LICENSE.md
Requires-Python: >=3.9
Requires-Dist: pycurl>=7.45.7
